SpliceV-0.2.0.0.data/scripts/RNABP.py
SpliceV-0.2.0.0.data/scripts/SpliceV
SpliceV-0.2.0.0.data/scripts/fa.py
SpliceV-0.2.0.0.data/scripts/find_circ_convert
SpliceV-0.2.0.0.data/scripts/star_sj_convert
SpliceV-0.2.0.0.dist-info/METADATA
SpliceV-0.2.0.0.dist-info/RECORD
SpliceV-0.2.0.0.dist-info/WHEEL
SpliceV-0.2.0.0.dist-info/top_level.txt
splicev/__init__.py
