Metadata-Version: 2.1
Name: SpliceV
Version: 0.2.0.0
Summary: Visualize splice junctions, backsplice junctions (circleRNA) and coverage from RNA-Seq datasets
Home-page: https://github.com/flemingtonlab/SpliceV
Author: Nathan Ungerleider
Author-email: nungerle@tulane.edu
License: UNKNOWN
Platform: UNKNOWN
Classifier: Programming Language :: Python :: 3
Classifier: License :: OSI Approved :: GNU General Public License v3 (GPLv3)
Classifier: Operating System :: OS Independent
Requires-Python: >=2.7,>=3
Requires-Dist: matplotlib
Requires-Dist: numpy
Requires-Dist: pysam
